CHANGELOG.md
LICENSE
MANIFEST.in
README.md
setup.cfg
setup.py
wagtailnetlify/__init__.py
wagtailnetlify/models.py
wagtailnetlify/urls.py
wagtailnetlify/views.py
wagtailnetlify/wagtail_hooks.py
wagtailnetlify.egg-info/PKG-INFO
wagtailnetlify.egg-info/SOURCES.txt
wagtailnetlify.egg-info/dependency_links.txt
wagtailnetlify.egg-info/not-zip-safe
wagtailnetlify.egg-info/pbr.json
wagtailnetlify.egg-info/requires.txt
wagtailnetlify.egg-info/top_level.txt
wagtailnetlify/management/__init__.py
wagtailnetlify/management/commands/__init__.py
wagtailnetlify/management/commands/netlify.py
wagtailnetlify/migrations/0001_initial.py
wagtailnetlify/migrations/__init__.py