Metadata-Version: 2.1
Name: wagtailnetlify
Version: 0.7
Summary: Deploy Wagtail sites to Netlify
Home-page: https://github.com/tomdyson/wagtail-netlify
Author: Tom Dyson
Author-email: tom+wagtailnetlify@torchbox.com
License: MIT
Keywords: development
Platform: UNKNOWN
Classifier: Environment :: Web Environment
Classifier: Framework :: Django
Classifier: Framework :: Wagtail
Classifier: Framework :: Wagtail :: 1
Classifier: Framework :: Wagtail :: 2
Classifier: Intended Audience :: Developers
Classifier: Operating System :: OS Independent
Classifier: Programming Language :: Python
Classifier: Topic :: Internet :: WWW/HTTP
Classifier: Topic :: Internet :: WWW/HTTP :: Dynamic Content
